gettextcodecs/methods.py
gettextcodecs-0.0.3.dist-info/LICENSE
gettextcodecs-0.0.3.dist-info/METADATA
gettextcodecs-0.0.3.dist-info/WHEEL
gettextcodecs-0.0.3.dist-info/top_level.txt
gettextcodecs-0.0.3.dist-info/RECORD
