Metadata-Version: 2.1
Name: gettextcodecs
Version: 0.0.3
Summary: Get python's text codecs
Home-page: http://gitlab.com/xoristzatziki/gettextcodecs
Author: Ηλίας Ηλιάδης
Author-email: iliadis@kekbay.gr
License: GPLv3
Platform: UNKNOWN
Classifier: Development Status :: 5 - Production/Stable
Classifier: Intended Audience :: Developers
Classifier: License :: OSI Approved :: GNU General Public License v3 or later (GPLv3+)
Classifier: Operating System :: OS Independent
Classifier: Programming Language :: Python :: 3
Classifier: Topic :: Software Development :: Libraries :: Python Modules
